cpass.py
cpass-0.9.4.data/data/share/doc/cpass/CHANGELOG
cpass-0.9.4.data/data/share/doc/cpass/Readme.md
cpass-0.9.4.data/data/share/doc/cpass/cpass.cfg
cpass-0.9.4.dist-info/LICENSE
cpass-0.9.4.dist-info/METADATA
cpass-0.9.4.dist-info/WHEEL
cpass-0.9.4.dist-info/entry_points.txt
cpass-0.9.4.dist-info/top_level.txt
cpass-0.9.4.dist-info/RECORD
