Metadata-Version: 2.1
Name: cpass
Version: 0.9.4
Summary: A TUI for pass, the standard Unix password manager
Home-page: https://github.com/OliverLew/cpass
Author: Lu Xu
Author-email: oliver_lew@outlook.com
License: MIT
Platform: UNKNOWN
Classifier: Development Status :: 3 - Alpha
Classifier: License :: OSI Approved :: MIT License
Classifier: Programming Language :: Python :: 3
Requires-Python: >=3
License-File: LICENSE
Requires-Dist: urwid
